keymap_drawer/__init__.py
keymap_drawer/__main__.py
keymap_drawer/config.py
keymap_drawer/draw/__init__.py
keymap_drawer/draw/combo.py
keymap_drawer/draw/draw.py
keymap_drawer/draw/glyph.py
keymap_drawer/draw/utils.py
keymap_drawer/dts.py
keymap_drawer/keymap.py
keymap_drawer/parse/__init__.py
keymap_drawer/parse/kanata.py
keymap_drawer/parse/parse.py
keymap_drawer/parse/qmk.py
keymap_drawer/parse/zmk.py
keymap_drawer/physical_layout.py
keymap_drawer/py.typed
resources/README.md
resources/extra_layouts/adv360.json
resources/extra_layouts/apiaster.json
resources/extra_layouts/bastardkb@charybdis@3x5.json
resources/extra_layouts/bastardkb@charybdis@3x6.json
resources/extra_layouts/bastardkb@charybdis@4x6.json
resources/extra_layouts/bastardkb@dilemma@3x5_3.json
resources/extra_layouts/bastardkb@dilemma@4x6_4.json
resources/extra_layouts/bastardkb@scylla.json
resources/extra_layouts/bastardkb@skeletyl.json
resources/extra_layouts/bastardkb@tbkmini.json
resources/extra_layouts/berylline.json
resources/extra_layouts/bluebell@swoop.json
resources/extra_layouts/chocofi.json
resources/extra_layouts/clog.json
resources/extra_layouts/corne_rotated.json
resources/extra_layouts/eyelash_corne.json
resources/extra_layouts/eyelash_sofle.json
resources/extra_layouts/ferris_rotated.json
resources/extra_layouts/fingerpunch@ffkb_rotated.json
resources/extra_layouts/fingerpunch@luakeeb.json
resources/extra_layouts/fingerpunch@vulpes_majora@v1.json
resources/extra_layouts/forager.json
resources/extra_layouts/glove80.json
resources/extra_layouts/grumpy.json
resources/extra_layouts/hazel@cut_slope.json
resources/extra_layouts/hazel@kurp.json
resources/extra_layouts/hummingbird.json
resources/extra_layouts/klor.json
resources/extra_layouts/klotz.json
resources/extra_layouts/kyria_rotated.json
resources/extra_layouts/lily58_rotated.json
resources/extra_layouts/lintilla.json
resources/extra_layouts/lotus58_rotated.json
resources/extra_layouts/menura.json
resources/extra_layouts/osprey.json
keymap_drawer-0.22.0.dist-info/LICENSE
keymap_drawer-0.22.0.dist-info/METADATA
keymap_drawer-0.22.0.dist-info/WHEEL
keymap_drawer-0.22.0.dist-info/entry_points.txt
keymap_drawer-0.22.0.dist-info/RECORD
