Metadata-Version: 2.3
Name: keymap-drawer
Version: 0.22.0
Summary: A module and CLI tool to help parse and draw keyboard layouts.
License: MIT
Author: Cem Aksoylar
Author-email: caksoylar@gmail.com
Requires-Python: >=3.12,<4.0
Classifier: License :: OSI Approved :: MIT License
Classifier: Programming Language :: Python :: 3
Classifier: Programming Language :: Python :: 3.12
Classifier: Programming Language :: Python :: 3.13
Provides-Extra: dev
Provides-Extra: lsp
Requires-Dist: black ; extra == "dev"
Requires-Dist: deptry (>=0.22.0) ; extra == "dev"
Requires-Dist: hjson ; extra == "dev"
Requires-Dist: mypy ; extra == "dev"
Requires-Dist: pcpp (>=1.30,<2.0)
Requires-Dist: platformdirs (>=4.0,<5.0)
Requires-Dist: pydantic (>=2.0,<3.0)
Requires-Dist: pydantic-settings (>=2.2,<3.0)
Requires-Dist: pylint ; extra == "dev"
Requires-Dist: pylint-pydantic ; extra == "dev"
Requires-Dist: pyparsing (>=3.2,<4.0)
Requires-Dist: python-lsp-server ; extra == "lsp"
Requires-Dist: pyyaml (>=6.0,<7.0)
Requires-Dist: tree-sitter (>=0.24,<1.0)
Requires-Dist: tree-sitter-devicetree (>=0.14,<1.0)
Requires-Dist: types-pyyaml ; extra == "dev"
Project-URL: Homepage, https://github.com/caksoylar/keymap-drawer
Project-URL: Repository, https://github.com/caksoylar/keymap-drawer
Project-URL: issues, https://github.com/caksoylar/keymap-drawer/issues
Project-URL: releasenotes, https://github.com/caksoylar/keymap-drawer/releases
